pixoo1664/__init__.py
pixoo1664-1.0.2.dist-info/LICENSE
pixoo1664-1.0.2.dist-info/METADATA
pixoo1664-1.0.2.dist-info/WHEEL
pixoo1664-1.0.2.dist-info/top_level.txt
pixoo1664-1.0.2.dist-info/RECORD
