Metadata-Version: 2.1
Name: pixoo1664
Version: 1.0.2
Summary: Unofficial Divoom pixoo REST library, beer not included.
Author-email: Yoann Le Viavant <yleviavant@gmail.com>
Project-URL: Homepage, https://github.com/Yo1L/pixoo1664
Project-URL: Issues, https://github.com/Yo1L/pixoo1664/issues
Classifier: Programming Language :: Python :: 3
Classifier: License :: OSI Approved :: MIT License
Classifier: Operating System :: OS Independent
Requires-Python: >=3.8
License-File: LICENSE
Requires-Dist: requests ~=2.31.0
Requires-Dist: Pillow >=6.2.1
